Workbook

Sheet Итог
A1: Вводные данные
A2: Количество покупателей | B2: 20000
A3: MDE | B3: 500
A4: Расчетные данные
A5: Прибыль | B5: =SUM('Positive outcome'!P2:P18) -> 5255440.1
A6: Потери | B6: =SUM('Negative outcome'!P2:P4) -> -506430.33
A7: Баланс | B7: =B5+B6 -> 4749009.8
A8: Количество наблюдений | B8: =SUM('Neutral outcome'!P2:P34) -> 15942.366

Sheet Positive outcome
B1: city | C1: id_trading_point | D1: count_test | E1: count_control | F1: count_all | G1: percent_count | H1: avg_payment_test | I1: avg_payment_control | J1: diff | K1: sigma_test | L1: sigma_control | M1: ttest | N1: pvalue_ttest | O1: label | P1: revenue growth
A2: 8 | B2: Казань | C2: 991 | D2: 270 | E2: 294 | F2: 564 | G2: 1.2303397 | H2: 3249.2815 | I2: 2452.9864 | J2: 796.29509 | K2: 4719.5926 | L2: 3633.9359 | M2: -2.2552584 | N2: 0.024501005 | O2: Positive outcome | P2: =J2*G2/100*Итог!$B$2 -> 195942.68
A3: 14 | B3: Санкт-Петербург | C3: 453 | D3: 1066 | E3: 1049 | F3: 2115 | G3: 4.6137737 | H3: 2501.9662 | I3: 1889.9237 | J3: 612.04249 | K3: 2993.4425 | L3: 2648.6593 | M3: -4.9769102 | N3: 6.9832069e-07 | O3: Positive outcome | P3: =J3*G3/100*Итог!$B$2 -> 564765.11
A4: 17 | B4: Санкт-Петербург | C4: 801 | D4: 225 | E4: 212 | F4: 437 | G4: 0.95329509 | H4: 2925.1422 | I4: 2352.283 | J4: 572.8592 | K4: 2774.2921 | L4: 2928.2858 | M4: -2.0999906 | N4: 0.036305006 | O4: Positive outcome | P4: =J4*G4/100*Итог!$B$2 -> 109220.77
A5: 18 | B5: Санкт-Петербург | C5: 573 | D5: 177 | E5: 160 | F5: 337 | G5: 0.73514976 | H5: 2929.0452 | I5: 1641.2125 | J5: 1287.8327 | K5: 3201.0981 | L5: 2619.0448 | M5: -4.0165685 | N5: 7.2940741e-05 | O5: Positive outcome | P5: =J5*G5/100*Итог!$B$2 -> 189349.98
A6: 21 | B6: Санкт-Петербург | C6: 900 | D6: 335 | E6: 341 | F6: 676 | G6: 1.4746624 | H6: 2450.991 | I6: 1689.7918 | J6: 761.19926 | K6: 2865.6074 | L6: 2492.4726 | M6: -3.6869136 | N6: 0.00024525342 | O6: Positive outcome | P6: =J6*G6/100*Итог!$B$2 -> 224502.39
A7: 22 | B7: Санкт-Петербург | C7: 117 | D7: 625 | E7: 587 | F7: 1212 | G7: 2.6439214 | H7: 2582.2976 | I7: 2050.6917 | J7: 531.60595 | K7: 2835.0045 | L7: 2595.7378 | M7: -3.3981956 | N7: 0.00070038166 | O7: Positive outcome | P7: =J7*G7/100*Итог!$B$2 -> 281104.87
A8: 23 | B8: Санкт-Петербург | C8: 213 | D8: 232 | E8: 255 | F8: 487 | G8: 1.0623677 | H8: 2977.6293 | I8: 2277.6118 | J8: 700.01755 | K8: 2905.4944 | L8: 2710.0434 | M8: -2.7507519 | N8: 0.0061682153 | O8: Positive outcome | P8: =J8*G8/100*Итог!$B$2 -> 148735.21
A9: 24 | B9: Санкт-Петербург | C9: 891 | D9: 159 | E9: 167 | F9: 326 | G9: 0.71115377 | H9: 2618.9497 | I9: 1980.6587 | J9: 638.291 | K9: 2899.7825 | L9: 2489.5719 | M9: -2.1355935 | N9: 0.033462037 | O9: Positive outcome | P9: =J9*G9/100*Итог!$B$2 -> 90784.611
A10: 25 | B10: Москва | C10: 2652 | D10: 2273 | E10: 2370 | F10: 4643 | G10: 10.128488 | H10: 2508.8896 | I10: 1972.8477 | J10: 536.04189 | K10: 2846.6365 | L10: 2565.8782 | M10: -6.7451371 | N10: 1.716201e-11 | O10: Positive outcome | P10: =J10*G10/100*Итог!$B$2 -> 1085858.7
A11: 27 | B11: Москва | C11: 1287 | D11: 370 | E11: 357 | F11: 727 | G11: 1.5859165 | H11: 2143.4892 | I11: 1394.6555 | J11: 748.83373 | K11: 2441.2219 | L11: 2338.4618 | M11: -4.2210099 | N11: 2.741105e-05 | O11: Positive outcome | P11: =J11*G11/100*Итог!$B$2 -> 237517.56
A12: 31 | B12: Москва | C12: 1654 | D12: 799 | E12: 775 | F12: 1574 | G12: 3.4336075 | H12: 3176.433 | I12: 2507.8865 | J12: 668.54659 | K12: 3208.0518 | L12: 2950.5129 | M12: -4.2997978 | N12: 1.8146601e-05 | O12: Positive outcome | P12: =J12*G12/100*Итог!$B$2 -> 459105.31
A13: 35 | B13: Москва | C13: 1002 | D13: 138 | E13: 188 | F13: 326 | G13: 0.71115377 | H13: 4144.8551 | I13: 1844.7872 | J13: 2300.0678 | K13: 4069.7698 | L13: 2436.5361 | M13: -6.3534484 | N13: 7.1299585e-10 | O13: Positive outcome | P13: =J13*G13/100*Итог!$B$2 -> 327140.38
... A18: 47 | B18: Самара | C18: 36 | D18: 131 | E18: 141 | F18: 272 | G18: 0.59335529 | H18: 1987.3282 | I18: 860.41844 | J18: 1126.9098 | K18: 2718.5027 | L18: 1840.8266 | M18: -4.0279507 | N18: 7.3187581e-05 | O18: Positive outcome | P18: =J18*G18/100*Итог!$B$2 -> 133731.58
P19: =SUM(P2:P18) -> 5255440.1

Sheet Negative outcome
B1: city | C1: id_trading_point | D1: count_test | E1: count_control | F1: count_all | G1: percent_count | H1: avg_payment_test | I1: avg_payment_control | J1: diff | K1: sigma_test | L1: sigma_control | M1: ttest | N1: pvalue_ttest | O1: label | P1: revenue drop
A2: 33 | B2: Москва | C2: 9931 | D2: 153 | E2: 137 | F2: 290 | G2: 0.63262145 | H2: 1415.7843 | I2: 1968.6934 | J2: -552.90912 | K2: 2038.1642 | L2: 2403.3979 | M2: 2.1191969 | N2: 0.034929469 | O2: Negative outcome | P2: =J2*G2/100*Итог!$B$2 -> -69956.434
A3: 40 | B3: Волгоград | C3: 66 | D3: 657 | E3: 703 | F3: 1360 | G3: 2.9667765 | H3: 2288.8706 | I3: 2601.761 | J3: -312.8904 | K3: 2682.5676 | L3: 2830.1938 | M3: 2.0892719 | N3: 0.036868999 | O3: Negative outcome | P3: =J3*G3/100*Итог!$B$2 -> -185655.18
A4: 48 | B4: Краснодар | C4: 1101 | D4: 785 | E4: 869 | F4: 1654 | G4: 3.6081237 | H4: 2176.0038 | I4: 2523.5788 | J4: -347.575 | K4: 2722.6245 | L4: 2960.3523 | M4: 2.4767363 | N4: 0.013358448 | O4: Negative outcome | P4: =J4*G4/100*Итог!$B$2 -> -250818.72
P5: =SUM(P2:P4) -> -506430.33

Sheet Neutral outcome
B1: city | C1: id_trading_point | D1: count_test | E1: count_control | F1: count_all | G1: percent_count | H1: avg_payment_test | I1: avg_payment_control | J1: diff | K1: sigma_test | L1: sigma_control | M1: ttest | N1: pvalue_ttest | O1: label | P1: cnt_observ
A2: 0 | B2: Красноярск | C2: 212 | D2: 593 | E2: 575 | F2: 1168 | G2: 2.5479374 | H2: 2144.317 | I2: 2222.0522 | J2: -77.735142 | K2: 2708.5887 | L2: 2785.1163 | M2: 0.48358539 | N2: 0.62877095 | O2: Neutral outcome | P2: =16*(MIN(K2,L2)^2)/(Итог!$B$3^2) -> 469.53298
A3: 1 | B3: Красноярск | C3: 278 | D3: 535 | E3: 489 | F3: 1024 | G3: 2.2338082 | H3: 2499.3458 | I3: 2185.2147 | J3: 314.13107 | K3: 2915.9953 | L3: 2574.9156 | M3: -1.8202681 | N3: 0.069010561 | O3: Neutral outcome | P3: =16*(MIN(K3,L3)^2)/(Итог!$B$3^2) -> 424.33218
A4: 2 | B4: Красноярск | C4: 202 | D4: 551 | E4: 565 | F4: 1116 | G4: 2.4345019 | H4: 2927.3412 | I4: 2730.3788 | J4: 196.96244 | K4: 2956.6862 | L4: 2737.8858 | M4: -1.1550729 | N4: 0.24830826 | O4: Neutral outcome | P4: =16*(MIN(K4,L4)^2)/(Итог!$B$3^2) -> 479.74519
A5: 3 | B5: Красноярск | C5: 444 | D5: 650 | E5: 562 | F5: 1212 | G5: 2.6439214 | H5: 2404.1062 | I5: 2545.7349 | J5: -141.62872 | K5: 2810.8285 | L5: 2797.1388 | M5: 0.87674037 | N5: 0.3808017 | O5: Neutral outcome | P5: =16*(MIN(K5,L5)^2)/(Итог!$B$3^2) -> 500.73506
A6: 4 | B6: Красноярск | C6: 277 | D6: 708 | E6: 709 | F6: 1417 | G6: 3.0911193 | H6: 2285.75 | I6: 2431.3653 | J6: -145.6153 | K6: 2712.6779 | L6: 2868.5876 | M6: 0.98170547 | N6: 0.32641279 | O6: Neutral outcome | P6: =16*(MIN(K6,L6)^2)/(Итог!$B$3^2) -> 470.95176
A7: 5 | B7: Нижний Новгород | C7: 13 | D7: 142 | E7: 150 | F7: 292 | G7: 0.63698436 | H7: 1970.5493 | I7: 2336.1867 | J7: -365.63737 | K7: 2575.9448 | L7: 2709.8955 | M7: 1.1803813 | N7: 0.23881587 | O7: Neutral outcome | P7: =16*(MIN(K7,L7)^2)/(Итог!$B$3^2) -> 424.67145
A8: 6 | B8: Мурманск | C8: 54 | D8: 633 | E8: 640 | F8: 1273 | G8: 2.77699 | H8: 1702.7141 | I8: 1688.5125 | J8: 14.20156 | K8: 2565.1324 | L8: 2628.0125 | M8: -0.097555657 | N8: 0.92230052 | O8: Neutral outcome | P8: =16*(MIN(K8,L8)^2)/(Итог!$B$3^2) -> 421.11388
A9: 7 | B9: Мурманск | C9: 55 | D9: 422 | E9: 425 | F9: 847 | G9: 1.8476909 | H9: 2109.1066 | I9: 2111.2729 | J9: -2.1663061 | K9: 2790.9934 | L9: 2804.2232 | M9: 0.011267746 | N9: 0.99101249 | O9: Neutral outcome | P9: =16*(MIN(K9,L9)^2)/(Итог!$B$3^2) -> 498.53722
A10: 9 | B10: Казань | C10: 699 | D10: 482 | E10: 494 | F10: 976 | G10: 2.1290984 | H10: 2422.2863 | I10: 2574.3522 | J10: -152.06592 | K10: 3906.8179 | L10: 4082.8514 | M10: 0.59425383 | N10: 0.55248036 | O10: Neutral outcome | P10: =16*(MIN(K10,L10)^2)/(Итог!$B$3^2) -> 976.84647
A11: 10 | B11: Казань | C11: 477 | D11: 382 | E11: 386 | F11: 768 | G11: 1.6753561 | H11: 2259.623 | I11: 2496.987 | J11: -237.36401 | K11: 3482.8461 | L11: 3881.9947 | M11: 0.89159336 | N11: 0.3728909 | O11: Neutral outcome | P11: =16*(MIN(K11,L11)^2)/(Итог!$B$3^2) -> 776.33388
A12: 11 | B12: Казань | C12: 544 | D12: 377 | E12: 416 | F12: 793 | G12: 1.7298925 | H12: 2621.4271 | I12: 2635.5481 | J12: -14.121021 | K12: 3714.8948 | L12: 4639.8207 | M12: 0.04699706 | N12: 0.96252743 | O12: Neutral outcome | P12: =16*(MIN(K12,L12)^2)/(Итог!$B$3^2) -> 883.22835
A13: 12 | B13: Казань | C13: 516 | D13: 634 | E13: 636 | F13: 1270 | G13: 2.7704457 | H13: 3245.2003 | I13: 2880.4843 | J13: 364.71604 | K13: 4543.1693 | L13: 3819.2928 | M13: -1.5486734 | N13: 0.12170978 | O13: Neutral outcome | P13: =16*(MIN(K13,L13)^2)/(Итог!$B$3^2) -> 933.56785
... A34: 52 | B34: Дмитров | C34: 2 | D34: 78 | E34: 71 | F34: 149 | G34: 0.32503654 | H34: 579.33333 | I34: 483.4507 | J34: 95.882629 | K34: 1860.7624 | L34: 1654.9232 | M34: -0.33105243 | N34: 0.74107631 | O34: Neutral outcome | P34: =16*(MIN(K34,L34)^2)/(Итог!$B$3^2) -> 175.28133
P35: =SUM(P2:P34) -> 15942.366
